{
	"name": "PAUTGSQLP23_AndeanDB_SistemaProducto",
	"properties": {
		"linkedServiceName": {
			"referenceName": "PAUTGSQLP23_ANDEANDB",
			"type": "LinkedServiceReference"
		},
		"annotations": [],
		"type": "SqlServerTable",
		"schema": [
			{
				"name": "CodigoProducto",
				"type": "varchar"
			},
			{
				"name": "CodigoSistema",
				"type": "varchar"
			},
			{
				"name": "CodigoProductoSistema",
				"type": "varchar"
			}
		],
		"typeProperties": {
			"schema": "dbo",
			"table": "SistemaProducto"
		}
	},
	"type": "Microsoft.DataFactory/factories/datasets"
}