{
	"name": "sqldbgdadev_ClasificacionProducto",
	"properties": {
		"linkedServiceName": {
			"referenceName": "srvsqlazsourcesdev_sqldbgdadev",
			"type": "LinkedServiceReference"
		},
		"annotations": [],
		"type": "AzureSqlTable",
		"schema": [
			{
				"name": "CodigoClasificacionProducto",
				"type": "varchar"
			},
			{
				"name": "NombreClasificacionProducto",
				"type": "varchar"
			}
		],
		"typeProperties": {
			"schema": "ANDEANDB",
			"table": "ClasificacionProducto"
		}
	},
	"type": "Microsoft.DataFactory/factories/datasets"
}